pynumeral/__init__.py
pynumeral/pynumeral.py
pynumeral-0.1.2.dist-info/DESCRIPTION.rst
pynumeral-0.1.2.dist-info/METADATA
pynumeral-0.1.2.dist-info/RECORD
pynumeral-0.1.2.dist-info/WHEEL
pynumeral-0.1.2.dist-info/metadata.json
pynumeral-0.1.2.dist-info/top_level.txt
