Metadata-Version: 2.0
Name: pynumeral
Version: 0.1.2
Summary: Python implementation of numeraljs
Home-page: https://github.com/gtnx/pynumeral
Author: Guillaume Thomas
Author-email: guillaume.thomas@optimdata.eu
License: MIT license
Keywords: pynumeral
Platform: UNKNOWN
Classifier: Development Status :: 2 - Pre-Alpha
Classifier: Intended Audience :: Developers
Classifier: License :: OSI Approved :: MIT License
Classifier: Natural Language :: English
Classifier: Programming Language :: Python :: 2
Classifier: Programming Language :: Python :: 2.7
Classifier: Programming Language :: Python :: 3
Classifier: Programming Language :: Python :: 3.4
Classifier: Programming Language :: Python :: 3.5
Classifier: Programming Language :: Python :: 3.6
Classifier: Programming Language :: Python :: 3.7
